setup.py
frasco_emails/__init__.py
frasco_emails.egg-info/PKG-INFO
frasco_emails.egg-info/SOURCES.txt
frasco_emails.egg-info/dependency_links.txt
frasco_emails.egg-info/not-zip-safe
frasco_emails.egg-info/requires.txt
frasco_emails.egg-info/top_level.txt
frasco_emails/templates/layout.html
frasco_emails/templates/layouts/MAILGUN_LICENSE
frasco_emails/templates/layouts/MAILGUN_README.md
frasco_emails/templates/layouts/alert.html
frasco_emails/templates/layouts/base.html
frasco_emails/templates/layouts/invoice.html
frasco_emails/templates/layouts/macros.html
frasco_emails/templates/layouts/markdown.html
frasco_emails/templates/layouts/text.html