Metadata-Version: 1.0
Name: frasco-emails
Version: 0.4
Summary: Emails sending for Frasco
Home-page: http://github.com/frascoweb/frasco-emails
Author: Maxime Bouroumeau-Fuseau
Author-email: maxime.bouroumeau@gmail.com
License: MIT
Platform: any
